src/__init__.py
src/main.py
src/helpers/__init__.py
src/helpers/lsp.py
src/helpers/treesitter.py
vendor/__init__.py
lsp_tree_finder-0.1.dist-info/METADATA
lsp_tree_finder-0.1.dist-info/WHEEL
lsp_tree_finder-0.1.dist-info/entry_points.txt
lsp_tree_finder-0.1.dist-info/top_level.txt
lsp_tree_finder-0.1.dist-info/RECORD
